pylogicalprogram/__init__.py
pylogicalprogram/logical/__init__.py
pylogicalprogram/logical/armstrongnumber.py
pylogicalprogram/logical/binarysearch.py
pylogicalprogram/logical/factorial.py
pylogicalprogram/logical/fibonacciseries.py
pylogicalprogram/logical/integertoroman.py
pylogicalprogram/logical/linearsearch.py
pylogicalprogram/logical/missingnumber.py
pylogicalprogram/logical/multiplicationtable.py
pylogicalprogram/logical/numberdigitcount.py
pylogicalprogram/logical/numberofisland.py
pylogicalprogram/logical/numbertoword.py
pylogicalprogram/logical/parentheses.py
pylogicalprogram/logical/permutations.py
pylogicalprogram/logical/reverseinteger.py
pylogicalprogram/logical/romantointeger.py
pylogicalprogram/logical/spiralmatrix.py
pylogicalprogram/logical/stringnumberevaluation.py
pylogicalprogram/logical/stringreverseandpalindrome.py
pylogicalprogram/logical/swaptwonumbers.py
pylogicalprogram/logical/testjustification.py
pylogicalprogram/logical/zigzagconvertion.py
pylogicalprogram/patterns/Alphabetspatterns.py
pylogicalprogram/patterns/NumbersPattern.py
pylogicalprogram/patterns/Pypatterns.py
pylogicalprogram/patterns/__init__.py
pylogicalprogram/pythoninfo/__init__.py
pylogicalprogram/pythoninfo/getpythoninfo.py
pylogicalprogram/shift/__init__.py
pylogicalprogram/shift/leftShift.py
pylogicalprogram/shift/rightShift.py
pylogicalprogram/systeminfo/__init__.py
pylogicalprogram/systeminfo/getsysteminfo.py
pylogicalprogram-1.4.dist-info/LICENSE.txt
pylogicalprogram-1.4.dist-info/METADATA
pylogicalprogram-1.4.dist-info/WHEEL
pylogicalprogram-1.4.dist-info/top_level.txt
pylogicalprogram-1.4.dist-info/RECORD
