Metadata-Version: 2.1
Name: pylogicalprogram
Version: 1.4
Summary: A collection of logical and pattern programs in Python
Home-page: https://github.com/rdinesh808/pylogicalprograms
Author: rdinesh808
Author-email: rdinesh808@gmail.com
Classifier: Programming Language :: Python :: 3
Classifier: License :: OSI Approved :: MIT License
Classifier: Operating System :: OS Independent
Requires-Python: >=3.6
License-File: LICENSE.txt
Requires-Dist: psutil
